[{"CREATED":"Apr 18, 2018 9:49:10 PM","firstName":"Joe","middleNames":["Middle"],"lastName":"Bloggs","birth":{"year":1990,"month":2,"day":9},"height":0.0,"weight":0.0,"zip":0,"donations":["LIVER","CORNEA"],"modified":"Apr 18, 2018 9:49:10 PM","nhiNumber":"ABC1238","currentDiseases":[{"diseaseName":"Death Curse","dateDiagnosed":{"year":2018,"month":4,"day":28},"diseaseState":"CHRONIC"}],"pastDiseases":[{"diseaseName":"Influenza","dateDiagnosed":{"year":2018,"month":4,"day":28},"diseaseState":"CURED"}]}]